README.md
setup.cfg
setup.py
joinnector/__init__.py
joinnector.egg-info/PKG-INFO
joinnector.egg-info/SOURCES.txt
joinnector.egg-info/dependency_links.txt
joinnector.egg-info/requires.txt
joinnector.egg-info/top_level.txt
joinnector/client/__init__.py
joinnector/client/delegate_client.py
joinnector/client/logging_client.py
joinnector/client/request_client.py
joinnector/client/security_client.py
joinnector/helper/__init__.py
joinnector/helper/collection_helper.py
joinnector/helper/constant_helper.py
joinnector/helper/sub_contant_helper/__init__.py
joinnector/helper/sub_contant_helper/setting_constant_helper.py
joinnector/service/__init__.py
joinnector/service/base_sdk_service.py
joinnector/service/coupon_service.py
joinnector/service/currency_service.py
joinnector/service/deal_service.py
joinnector/service/lead_service.py
joinnector/service/notification_service.py
joinnector/service/offer_service.py
joinnector/service/review_service.py
joinnector/service/setting_service.py
joinnector/service/store_service.py
joinnector/service/surprise_service.py
joinnector/service/surpriseactivity_service.py
joinnector/service/swap_service.py
joinnector/service/task_service.py
joinnector/service/taskactivity_service.py
joinnector/service/wallet_service.py
joinnector/service/wallettransaction_service.py
joinnector/wrapper/__init__.py
joinnector/wrapper/logging_wrapper.py
joinnector/wrapper/request_wrapper.py
joinnector/wrapper/security_wrapper.py