Metadata-Version: 1.1
Name: joinnector
Version: 10.0
Summary: Nector python SDK (nector provides a suite of plug-n-play APIs & SDK focused on rewarding customers, driving customer engagements and improving sales, for the businesses.)
Home-page: https://github.com/joinnector/joinnector-python-sdk
Author: Tech, Nector
Author-email: tech@nector.io
License: MIT
Download-URL: https://github.com/joinnector/joinnector-python-sdk/archive/10.0.tar.gz
Keywords: nector,reward,loyalty,coins,wallets,deals
Platform: UNKNOWN
Classifier: Development Status :: 4 - Beta
Classifier: Intended Audience :: Developers
Classifier: Topic :: Software Development :: Build Tools
Classifier: License :: OSI Approved :: MIT License
Classifier: Programming Language :: Python :: 3
Classifier: Programming Language :: Python :: 3.4
Classifier: Programming Language :: Python :: 3.5
Classifier: Programming Language :: Python :: 3.6
